fractale/__init__.py
fractale/_schema.py
fractale/defaults.py
fractale/jobspec.py
fractale/utils.py
fractale/version.py
fractale/_core/__init__.py
fractale/_core/base.py
fractale/_core/converter.py
fractale/_core/core.py
fractale/_core/resources.py
fractale/_plugin/__init__.py
fractale/_steps/__init__.py
fractale/_steps/base.py
fractale/_steps/empty.py
fractale/_steps/fileio.py
fractale/_steps/runner.py
fractale/agent/__init__.py
fractale/agent/base.py
fractale/agent/context.py
fractale/agent/decorators.py
fractale/agent/defaults.py
fractale/agent/logger.py
fractale/agent/parser.py
fractale/agent/prompts.py
fractale/agent/build/__init__.py
fractale/agent/build/agent.py
fractale/agent/build/prompts.py
fractale/agent/errors/__init__.py
fractale/agent/errors/agent.py
fractale/agent/errors/prompts.py
fractale/agent/kubernetes/__init__.py
fractale/agent/kubernetes/base.py
fractale/agent/kubernetes/objects.py
fractale/agent/kubernetes/prompts.py
fractale/agent/kubernetes/job/__init__.py
fractale/agent/kubernetes/job/agent.py
fractale/agent/kubernetes/job/prompts.py
fractale/agent/kubernetes/minicluster/__init__.py
fractale/agent/kubernetes/minicluster/agent.py
fractale/agent/kubernetes/minicluster/prompts.py
fractale/agent/kubernetes_job/__init__.py
fractale/agent/kubernetes_job/agent.py
fractale/agent/kubernetes_job/prompts.py
fractale/agent/manager/__init__.py
fractale/agent/manager/agent.py
fractale/agent/manager/plan.py
fractale/agent/manager/prompts.py
fractale/agent/optimize/__init__.py
fractale/agent/optimize/agent.py
fractale/agent/optimize/prompts.py
fractale/agent/results/__init__.py
fractale/agent/results/agent.py
fractale/agent/results/prompts.py
fractale/cli/__init__.py
fractale/cli/agent.py
fractale/cli/generate_subsystem.py
fractale/cli/satisfy.py
fractale/cli/save.py
fractale/cli/script.py
fractale/cli/transform.py
fractale/logger/__init__.py
fractale/logger/generate.py
fractale/logger/logger.py
fractale/selector/__init__.py
fractale-0.0.13.dist-info/LICENSE
fractale-0.0.13.dist-info/METADATA
fractale-0.0.13.dist-info/NOTICE
fractale-0.0.13.dist-info/WHEEL
fractale-0.0.13.dist-info/entry_points.txt
fractale-0.0.13.dist-info/top_level.txt
fractale-0.0.13.dist-info/RECORD
